README.md
setup.py
mathjaxplugin/__init__.py
mathjaxplugin.egg-info/PKG-INFO
mathjaxplugin.egg-info/SOURCES.txt
mathjaxplugin.egg-info/dependency_links.txt
mathjaxplugin.egg-info/top_level.txt